llama_index/prompt_utils/guidance/__init__.py
llama_index/prompt_utils/guidance/base.py
llama_index_prompt_utils_guidance-0.0.1.dist-info/METADATA
llama_index_prompt_utils_guidance-0.0.1.dist-info/WHEEL
llama_index_prompt_utils_guidance-0.0.1.dist-info/RECORD
